nomad_json_parser/__init__.py
nomad_json_parser/apps/__init__.py
nomad_json_parser/example_uploads/__init__.py
nomad_json_parser/example_uploads/json_mapper/README.MD
nomad_json_parser/example_uploads/json_mapper/example_data.json
nomad_json_parser/example_uploads/json_mapper/example_mapper.json
nomad_json_parser/parsers/__init__.py
nomad_json_parser/parsers/parser.py
nomad_json_parser/schema_packages/__init__.py
nomad_json_parser/schema_packages/jsonimport.py
nomad_json_parser-1.1.0.dist-info/licenses/LICENSE
nomad_json_parser-1.1.0.dist-info/METADATA
nomad_json_parser-1.1.0.dist-info/WHEEL
nomad_json_parser-1.1.0.dist-info/entry_points.txt
nomad_json_parser-1.1.0.dist-info/top_level.txt
nomad_json_parser-1.1.0.dist-info/RECORD
