Metadata-Version: 2.4
Name: nomad-json-parser
Version: 1.1.0
Summary: A NOMAD parser plugin for parsing json files to entries.
Author-email: FAIRmat <fairmat@physik.hu-berlin.de>
Maintainer-email: FAIRmat <fairmat@physik.hu-berlin.de>
License: 
Project-URL: Repository, https://github.com/FAIRmat-NFDI/nomad-json-parser
Classifier: Intended Audience :: Developers
Classifier: Operating System :: OS Independent
Classifier: Programming Language :: Python
Classifier: Programming Language :: Python :: 3.10
Classifier: Programming Language :: Python :: 3.11
Classifier: Programming Language :: Python :: 3.12
Classifier: License :: OSI Approved :: MIT License
Requires-Python: >=3.10
License-File: LICENSE
Requires-Dist: nomad-lab>=1.3.16
Requires-Dist: python-magic-bin; sys_platform == "win32"
Requires-Dist: nomad-material-processing
Provides-Extra: dev
Requires-Dist: ruff; extra == "dev"
Requires-Dist: pytest; extra == "dev"
Requires-Dist: structlog; extra == "dev"
Requires-Dist: python-logstash>=0.4.6; extra == "dev"
Requires-Dist: nomad-lab[dev,infrastructure]; extra == "dev"
Dynamic: license-file
